aztarna/__init__.py
aztarna/__main__.py
aztarna/cmd.py
aztarna/commons.py
aztarna/helpers.py
aztarna/industrialrouters/__init__.py
aztarna/industrialrouters/scanner.py
aztarna/ros/__init__.py
aztarna/ros/commons.py
aztarna/ros/helpers.py
aztarna/ros/ros/__init__.py
aztarna/ros/ros/helpers.py
aztarna/ros/ros/scanner.py
aztarna/ros/sros/__init__.py
aztarna/ros/sros/helpers.py
aztarna/ros/sros/scanner.py
aztarna-1.0.dist-info/LICENSE
aztarna-1.0.dist-info/METADATA
aztarna-1.0.dist-info/WHEEL
aztarna-1.0.dist-info/entry_points.txt
aztarna-1.0.dist-info/top_level.txt
aztarna-1.0.dist-info/RECORD
